{"code":"9130038","data":[{"prefcode":"18","ja":{"prefecture":"福井県","address1":"坂井市","address2":"三国町黒目","address3":"","address4":""},"en":{"prefecture":"Fukui","address1":"Sakai-shi","address2":"Mikunicho Kurome","address3":"","address4":""}},{"prefcode":"18","ja":{"prefecture":"福井県","address1":"坂井市","address2":"三国町新保","address3":"","address4":""},"en":{"prefecture":"Fukui","address1":"Sakai-shi","address2":"Mikunicho Shimbo","address3":"","address4":""}},{"prefcode":"18","ja":{"prefecture":"福井県","address1":"坂井市","address2":"三国町山岸","address3":"","address4":""},"en":{"prefecture":"Fukui","address1":"Sakai-shi","address2":"Mikunicho Yamagishi","address3":"","address4":""}},{"prefcode":"18","ja":{"prefecture":"福井県","address1":"坂井市","address2":"三国町米納津","address3":"","address4":""},"en":{"prefecture":"Fukui","address1":"Sakai-shi","address2":"Mikunicho Yonozu","address3":"","address4":""}}]}
