{"code":"9690402","data":[{"prefcode":"07","ja":{"prefecture":"福島県","address1":"岩瀬郡鏡石町","address2":"池の台","address3":"","address4":""},"en":{"prefecture":"Fukushima","address1":"Kagamiishi-machi, Iwase-gun","address2":"Ikenodai","address3":"","address4":""}},{"prefcode":"07","ja":{"prefecture":"福島県","address1":"岩瀬郡鏡石町","address2":"大宮","address3":"","address4":""},"en":{"prefecture":"Fukushima","address1":"Kagamiishi-machi, Iwase-gun","address2":"Omiya","address3":"","address4":""}},{"prefcode":"07","ja":{"prefecture":"福島県","address1":"岩瀬郡鏡石町","address2":"河原","address3":"","address4":""},"en":{"prefecture":"Fukushima","address1":"Kagamiishi-machi, Iwase-gun","address2":"Kawara","address3":"","address4":""}},{"prefcode":"07","ja":{"prefecture":"福島県","address1":"岩瀬郡鏡石町","address2":"北町","address3":"","address4":""},"en":{"prefecture":"Fukushima","address1":"Kagamiishi-machi, Iwase-gun","address2":"Kitamachi","address3":"","address4":""}},{"prefcode":"07","ja":{"prefecture":"福島県","address1":"岩瀬郡鏡石町","address2":"新町","address3":"","address4":""},"en":{"prefecture":"Fukushima","address1":"Kagamiishi-machi, Iwase-gun","address2":"Shimmachi","address3":"","address4":""}},{"prefcode":"07","ja":{"prefecture":"福島県","address1":"岩瀬郡鏡石町","address2":"諏訪町","address3":"","address4":""},"en":{"prefecture":"Fukushima","address1":"Kagamiishi-machi, Iwase-gun","address2":"Suwamachi","address3":"","address4":""}},{"prefcode":"07","ja":{"prefecture":"福島県","address1":"岩瀬郡鏡石町","address2":"成田","address3":"","address4":""},"en":{"prefecture":"Fukushima","address1":"Kagamiishi-machi, Iwase-gun","address2":"Narita","address3":"","address4":""}},{"prefcode":"07","ja":{"prefecture":"福島県","address1":"岩瀬郡鏡石町","address2":"成田原町","address3":"","address4":""},"en":{"prefecture":"Fukushima","address1":"Kagamiishi-machi, Iwase-gun","address2":"Naritaharamachi","address3":"","address4":""}},{"prefcode":"07","ja":{"prefecture":"福島県","address1":"岩瀬郡鏡石町","address2":"成田東","address3":"","address4":""},"en":{"prefecture":"Fukushima","address1":"Kagamiishi-machi, Iwase-gun","address2":"Naritahigashi","address3":"","address4":""}},{"prefcode":"07","ja":{"prefecture":"福島県","address1":"岩瀬郡鏡石町","address2":"東河原","address3":"","address4":""},"en":{"prefecture":"Fukushima","address1":"Kagamiishi-machi, Iwase-gun","address2":"Higashikawara","address3":"","address4":""}}]}
