{"code":"9696265","data":[{"prefcode":"07","ja":{"prefecture":"福島県","address1":"大沼郡会津美里町","address2":"漆原北","address3":"","address4":""},"en":{"prefecture":"Fukushima","address1":"Aizumisato-machi, Onuma-gun","address2":"Urushiwarakita","address3":"","address4":""}},{"prefcode":"07","ja":{"prefecture":"福島県","address1":"大沼郡会津美里町","address2":"御蔵南","address3":"","address4":""},"en":{"prefecture":"Fukushima","address1":"Aizumisato-machi, Onuma-gun","address2":"Okuraminami","address3":"","address4":""}},{"prefcode":"07","ja":{"prefecture":"福島県","address1":"大沼郡会津美里町","address2":"川添","address3":"","address4":""},"en":{"prefecture":"Fukushima","address1":"Aizumisato-machi, Onuma-gun","address2":"Kawazoe","address3":"","address4":""}},{"prefcode":"07","ja":{"prefecture":"福島県","address1":"大沼郡会津美里町","address2":"館南","address3":"","address4":""},"en":{"prefecture":"Fukushima","address1":"Aizumisato-machi, Onuma-gun","address2":"Tateminami","address3":"","address4":""}},{"prefcode":"07","ja":{"prefecture":"福島県","address1":"大沼郡会津美里町","address2":"長光寺南","address3":"","address4":""},"en":{"prefecture":"Fukushima","address1":"Aizumisato-machi, Onuma-gun","address2":"Chokojiminami","address3":"","address4":""}},{"prefcode":"07","ja":{"prefecture":"福島県","address1":"大沼郡会津美里町","address2":"六地蔵","address3":"","address4":""},"en":{"prefecture":"Fukushima","address1":"Aizumisato-machi, Onuma-gun","address2":"Rokujizo","address3":"","address4":""}}]}
