{"code":"9170241","data":[{"prefcode":"18","ja":{"prefecture":"福井県","address1":"小浜市","address2":"池田","address3":"","address4":""},"en":{"prefecture":"Fukui","address1":"Obama-shi","address2":"Ikeda","address3":"","address4":""}},{"prefcode":"18","ja":{"prefecture":"福井県","address1":"小浜市","address2":"市場","address3":"","address4":""},"en":{"prefecture":"Fukui","address1":"Obama-shi","address2":"Ichiba","address3":"","address4":""}},{"prefcode":"18","ja":{"prefecture":"福井県","address1":"小浜市","address2":"遠敷","address3":"","address4":""},"en":{"prefecture":"Fukui","address1":"Obama-shi","address2":"Onyu","address3":"","address4":""}},{"prefcode":"18","ja":{"prefecture":"福井県","address1":"小浜市","address2":"検見坂","address3":"","address4":""},"en":{"prefecture":"Fukui","address1":"Obama-shi","address2":"Kemmizaka","address3":"","address4":""}},{"prefcode":"18","ja":{"prefecture":"福井県","address1":"小浜市","address2":"島","address3":"","address4":""},"en":{"prefecture":"Fukui","address1":"Obama-shi","address2":"Shima","address3":"","address4":""}},{"prefcode":"18","ja":{"prefecture":"福井県","address1":"小浜市","address2":"中村","address3":"","address4":""},"en":{"prefecture":"Fukui","address1":"Obama-shi","address2":"Nakamura","address3":"","address4":""}}]}
