{"code":"4410323","data":[{"prefcode":"23","ja":{"prefecture":"愛知県","address1":"豊川市","address2":"御津町金野","address3":"","address4":""},"en":{"prefecture":"Aichi","address1":"Toyokawa-shi","address2":"Kaneno, Mitocho","address3":"","address4":""}},{"prefcode":"23","ja":{"prefecture":"愛知県","address1":"豊川市","address2":"御津町金野青木","address3":"","address4":""},"en":{"prefecture":"Aichi","address1":"Toyokawa-shi","address2":"Kanenoaoki, Mitocho","address3":"","address4":""}},{"prefcode":"23","ja":{"prefecture":"愛知県","address1":"豊川市","address2":"御津町金野油田","address3":"","address4":""},"en":{"prefecture":"Aichi","address1":"Toyokawa-shi","address2":"Kanenoaburada, Mitocho","address3":"","address4":""}},{"prefcode":"23","ja":{"prefecture":"愛知県","address1":"豊川市","address2":"御津町金野石田","address3":"","address4":""},"en":{"prefecture":"Aichi","address1":"Toyokawa-shi","address2":"Kanenoishida, Mitocho","address3":"","address4":""}},{"prefcode":"23","ja":{"prefecture":"愛知県","address1":"豊川市","address2":"御津町金野稲場","address3":"","address4":""},"en":{"prefecture":"Aichi","address1":"Toyokawa-shi","address2":"Kanenoinaba, Mitocho","address3":"","address4":""}},{"prefcode":"23","ja":{"prefecture":"愛知県","address1":"豊川市","address2":"御津町金野岩本","address3":"","address4":""},"en":{"prefecture":"Aichi","address1":"Toyokawa-shi","address2":"Kanenoiwamoto, Mitocho","address3":"","address4":""}},{"prefcode":"23","ja":{"prefecture":"愛知県","address1":"豊川市","address2":"御津町金野上野","address3":"","address4":""},"en":{"prefecture":"Aichi","address1":"Toyokawa-shi","address2":"Kanenoeno, Mitocho","address3":"","address4":""}},{"prefcode":"23","ja":{"prefecture":"愛知県","address1":"豊川市","address2":"御津町金野籠田","address3":"","address4":""},"en":{"prefecture":"Aichi","address1":"Toyokawa-shi","address2":"Kanenokagota, Mitocho","address3":"","address4":""}},{"prefcode":"23","ja":{"prefecture":"愛知県","address1":"豊川市","address2":"御津町金野上沢","address3":"","address4":""},"en":{"prefecture":"Aichi","address1":"Toyokawa-shi","address2":"Kanenokamisawa, Mitocho","address3":"","address4":""}},{"prefcode":"23","ja":{"prefecture":"愛知県","address1":"豊川市","address2":"御津町金野観音寺","address3":"","address4":""},"en":{"prefecture":"Aichi","address1":"Toyokawa-shi","address2":"Kanenokannonji, Mitocho","address3":"","address4":""}},{"prefcode":"23","ja":{"prefecture":"愛知県","address1":"豊川市","address2":"御津町金野国坂","address3":"","address4":""},"en":{"prefecture":"Aichi","address1":"Toyokawa-shi","address2":"Kanenokunizaka, Mitocho","address3":"","address4":""}},{"prefcode":"23","ja":{"prefecture":"愛知県","address1":"豊川市","address2":"御津町金野郷作","address3":"","address4":""},"en":{"prefecture":"Aichi","address1":"Toyokawa-shi","address2":"Kanenogosaku, Mitocho","address3":"","address4":""}},{"prefcode":"23","ja":{"prefecture":"愛知県","address1":"豊川市","address2":"御津町金野五反田","address3":"","address4":""},"en":{"prefecture":"Aichi","address1":"Toyokawa-shi","address2":"Kanenogotanda, Mitocho","address3":"","address4":""}},{"prefcode":"23","ja":{"prefecture":"愛知県","address1":"豊川市","address2":"御津町金野小根沢","address3":"","address4":""},"en":{"prefecture":"Aichi","address1":"Toyokawa-shi","address2":"Kanenokonezawa, Mitocho","address3":"","address4":""}},{"prefcode":"23","ja":{"prefecture":"愛知県","address1":"豊川市","address2":"御津町金野猿沢","address3":"","address4":""},"en":{"prefecture":"Aichi","address1":"Toyokawa-shi","address2":"Kanenosarusawa, Mitocho","address3":"","address4":""}},{"prefcode":"23","ja":{"prefecture":"愛知県","address1":"豊川市","address2":"御津町金野下","address3":"","address4":""},"en":{"prefecture":"Aichi","address1":"Toyokawa-shi","address2":"Kanenoshita, Mitocho","address3":"","address4":""}},{"prefcode":"23","ja":{"prefecture":"愛知県","address1":"豊川市","address2":"御津町金野下ノ前","address3":"","address4":""},"en":{"prefecture":"Aichi","address1":"Toyokawa-shi","address2":"Kanenoshimonomae, Mitocho","address3":"","address4":""}},{"prefcode":"23","ja":{"prefecture":"愛知県","address1":"豊川市","address2":"御津町金野新砂田","address3":"","address4":""},"en":{"prefecture":"Aichi","address1":"Toyokawa-shi","address2":"Kanenoshinsunata, Mitocho","address3":"","address4":""}},{"prefcode":"23","ja":{"prefecture":"愛知県","address1":"豊川市","address2":"御津町金野新山影","address3":"","address4":""},"en":{"prefecture":"Aichi","address1":"Toyokawa-shi","address2":"Kanenoshinyamakage, Mitocho","address3":"","address4":""}},{"prefcode":"23","ja":{"prefecture":"愛知県","address1":"豊川市","address2":"御津町金野砂田","address3":"","address4":""},"en":{"prefecture":"Aichi","address1":"Toyokawa-shi","address2":"Kanenosunata, Mitocho","address3":"","address4":""}},{"prefcode":"23","ja":{"prefecture":"愛知県","address1":"豊川市","address2":"御津町金野竹入","address3":"","address4":""},"en":{"prefecture":"Aichi","address1":"Toyokawa-shi","address2":"Kanenotakeiri, Mitocho","address3":"","address4":""}},{"prefcode":"23","ja":{"prefecture":"愛知県","address1":"豊川市","address2":"御津町金野足見","address3":"","address4":""},"en":{"prefecture":"Aichi","address1":"Toyokawa-shi","address2":"Kanenotarumi, Mitocho","address3":"","address4":""}},{"prefcode":"23","ja":{"prefecture":"愛知県","address1":"豊川市","address2":"御津町金野徳寒","address3":"","address4":""},"en":{"prefecture":"Aichi","address1":"Toyokawa-shi","address2":"Kanenotokusabu, Mitocho","address3":"","address4":""}},{"prefcode":"23","ja":{"prefecture":"愛知県","address1":"豊川市","address2":"御津町金野中切","address3":"","address4":""},"en":{"prefecture":"Aichi","address1":"Toyokawa-shi","address2":"Kanenonakagiri, Mitocho","address3":"","address4":""}},{"prefcode":"23","ja":{"prefecture":"愛知県","address1":"豊川市","address2":"御津町金野中畑","address3":"","address4":""},"en":{"prefecture":"Aichi","address1":"Toyokawa-shi","address2":"Kanenonakabata, Mitocho","address3":"","address4":""}},{"prefcode":"23","ja":{"prefecture":"愛知県","address1":"豊川市","address2":"御津町金野西沢","address3":"","address4":""},"en":{"prefecture":"Aichi","address1":"Toyokawa-shi","address2":"Kanenonishizawa, Mitocho","address3":"","address4":""}},{"prefcode":"23","ja":{"prefecture":"愛知県","address1":"豊川市","address2":"御津町金野灰野坂","address3":"","address4":""},"en":{"prefecture":"Aichi","address1":"Toyokawa-shi","address2":"Kanenohainozaka, Mitocho","address3":"","address4":""}},{"prefcode":"23","ja":{"prefecture":"愛知県","address1":"豊川市","address2":"御津町金野長谷沢","address3":"","address4":""},"en":{"prefecture":"Aichi","address1":"Toyokawa-shi","address2":"Kanenohasezawa, Mitocho","address3":"","address4":""}},{"prefcode":"23","ja":{"prefecture":"愛知県","address1":"豊川市","address2":"御津町金野東河津","address3":"","address4":""},"en":{"prefecture":"Aichi","address1":"Toyokawa-shi","address2":"Kanenohigashikawazu, Mitocho","address3":"","address4":""}},{"prefcode":"23","ja":{"prefecture":"愛知県","address1":"豊川市","address2":"御津町金野東田","address3":"","address4":""},"en":{"prefecture":"Aichi","address1":"Toyokawa-shi","address2":"Kanenohigashida, Mitocho","address3":"","address4":""}},{"prefcode":"23","ja":{"prefecture":"愛知県","address1":"豊川市","address2":"御津町金野東畑","address3":"","address4":""},"en":{"prefecture":"Aichi","address1":"Toyokawa-shi","address2":"Kanenohigashibata, Mitocho","address3":"","address4":""}},{"prefcode":"23","ja":{"prefecture":"愛知県","address1":"豊川市","address2":"御津町金野桧河津","address3":"","address4":""},"en":{"prefecture":"Aichi","address1":"Toyokawa-shi","address2":"Kanenohinokikawazu, Mitocho","address3":"","address4":""}},{"prefcode":"23","ja":{"prefecture":"愛知県","address1":"豊川市","address2":"御津町金野深沢","address3":"","address4":""},"en":{"prefecture":"Aichi","address1":"Toyokawa-shi","address2":"Kanenofukazawa, Mitocho","address3":"","address4":""}},{"prefcode":"23","ja":{"prefecture":"愛知県","address1":"豊川市","address2":"御津町金野深田","address3":"","address4":""},"en":{"prefecture":"Aichi","address1":"Toyokawa-shi","address2":"Kanenofukada, Mitocho","address3":"","address4":""}},{"prefcode":"23","ja":{"prefecture":"愛知県","address1":"豊川市","address2":"御津町金野袋田","address3":"","address4":""},"en":{"prefecture":"Aichi","address1":"Toyokawa-shi","address2":"Kanenofukuroda, Mitocho","address3":"","address4":""}},{"prefcode":"23","ja":{"prefecture":"愛知県","address1":"豊川市","address2":"御津町金野藤ケ山","address3":"","address4":""},"en":{"prefecture":"Aichi","address1":"Toyokawa-shi","address2":"Kanenofujigayama, Mitocho","address3":"","address4":""}},{"prefcode":"23","ja":{"prefecture":"愛知県","address1":"豊川市","address2":"御津町金野藤久保","address3":"","address4":""},"en":{"prefecture":"Aichi","address1":"Toyokawa-shi","address2":"Kanenofujikubo, Mitocho","address3":"","address4":""}},{"prefcode":"23","ja":{"prefecture":"愛知県","address1":"豊川市","address2":"御津町金野見竹","address3":"","address4":""},"en":{"prefecture":"Aichi","address1":"Toyokawa-shi","address2":"Kanenomitake, Mitocho","address3":"","address4":""}},{"prefcode":"23","ja":{"prefecture":"愛知県","address1":"豊川市","address2":"御津町金野山影","address3":"","address4":""},"en":{"prefecture":"Aichi","address1":"Toyokawa-shi","address2":"Kanenoyamakage, Mitocho","address3":"","address4":""}},{"prefcode":"23","ja":{"prefecture":"愛知県","address1":"豊川市","address2":"御津町金野山本","address3":"","address4":""},"en":{"prefecture":"Aichi","address1":"Toyokawa-shi","address2":"Kanenoyamamoto, Mitocho","address3":"","address4":""}},{"prefcode":"23","ja":{"prefecture":"愛知県","address1":"豊川市","address2":"御津町金野横手","address3":"","address4":""},"en":{"prefecture":"Aichi","address1":"Toyokawa-shi","address2":"Kanenoyokote, Mitocho","address3":"","address4":""}}]}
